fib
fib/fibonacci
opt
opt/Addition
opt/fun/func
opt/subraction
