Metadata-Version: 1.1
Name: rak-arth
Version: 1.5.4
Summary: it does arthimatical operations
Home-page: http://pypi.python.org/pypi/rak_arth/
Author: santoshi
Author-email: santhoshi.medasani@gmail.com
License: OSI Approved
Download-URL: http://pypi.python.org/pypi/rak_arth/Download
Keywords: rak,add,sub,mul
Platform: UNKNOWN
Classifier: Development Status :: 4 - Beta
Classifier: Environment :: Console
Classifier: Environment :: Web Environment
Classifier: Intended Audience :: End Users/Desktop
Classifier: Intended Audience :: Developers
Classifier: Intended Audience :: System Administrators
Classifier: License :: OSI Approved :: Python Software Foundation License
Classifier: Operating System :: MacOS :: MacOS X
Classifier: Operating System :: Microsoft :: Windows
Classifier: Operating System :: POSIX
Classifier: Programming Language :: Python
Classifier: Topic :: Communications :: Email
Classifier: Topic :: Office/Business
Classifier: Topic :: Software Development :: Bug Tracking
